{
    "object": "list",
    "results": [
        {
            "object": "page",
            "id": "104d216d-fe8c-4574-a4ba-af5a1f01e076",
            "created_time": "2024-02-18T09:59:00.000Z",
            "last_edited_time": "2024-02-18T10:04:00.000Z",
            "created_by": {
                "object": "user",
                "id": "c83264a1-1c18-4e62-b06f-09afb04553ab"
            },
            "last_edited_by": {
                "object": "user",
                "id": "c83264a1-1c18-4e62-b06f-09afb04553ab"
            },
            "cover": null,
            "icon": null,
            "parent": {
                "type": "database_id",
                "database_id": "5d5f91b2-48ff-4656-9cc5-f0508bec0abc"
            },
            "archived": false,
            "properties": {
                "Start Time": {
                    "id": "V%40vk",
                    "type": "date",
                    "date": {
                        "start": "2024-02-17T00:00:00.000+00:00",
                        "end": null,
                        "time_zone": null
                    }
                },
                "End Time": {
                    "id": "WtZF",
                    "type": "date",
                    "date": {
                        "start": "2024-02-17T02:00:00.000+00:00",
                        "end": null,
                        "time_zone": null
                    }
                },
                "Title": {
                    "id": "title",
                    "type": "title",
                    "title": [
                        {
                            "type": "text",
                            "text": {
                                "content": "SYNC TEST!!!!",
                                "link": null
                            },
                            "annotations": {
                                "bold": false,
                                "italic": false,
                                "strikethrough": false,
                                "underline": false,
                                "code": false,
                                "color": "default"
                            },
                            "plain_text": "SYNC TEST!!!!",
                            "href": null
                        }
                    ]
                }
            },
            "url": "https://www.notion.so/SYNC-TEST-104d216dfe8c4574a4baaf5a1f01e076",
            "public_url": "https://foam-salamander-68d.notion.site/SYNC-TEST-104d216dfe8c4574a4baaf5a1f01e076"
        },
        {
            "object": "page",
            "id": "63564486-ecf8-4983-826c-db383b49da92",
            "created_time": "2024-02-18T09:44:00.000Z",
            "last_edited_time": "2024-02-18T10:04:00.000Z",
            "created_by": {
                "object": "user",
                "id": "c83264a1-1c18-4e62-b06f-09afb04553ab"
            },
            "last_edited_by": {
                "object": "user",
                "id": "c83264a1-1c18-4e62-b06f-09afb04553ab"
            },
            "cover": null,
            "icon": null,
            "parent": {
                "type": "database_id",
                "database_id": "5d5f91b2-48ff-4656-9cc5-f0508bec0abc"
            },
            "archived": false,
            "properties": {
                "Start Time": {
                    "id": "V%40vk",
                    "type": "date",
                    "date": {
                        "start": "2024-02-07T21:30:00.000+00:00",
                        "end": null,
                        "time_zone": null
                    }
                },
                "End Time": {
                    "id": "WtZF",
                    "type": "date",
                    "date": {
                        "start": "2024-02-08T02:15:00.000+00:00",
                        "end": null,
                        "time_zone": null
                    }
                },
                "Title": {
                    "id": "title",
                    "type": "title",
                    "title": [
                        {
                            "type": "text",
                            "text": {
                                "content": "grind",
                                "link": null
                            },
                            "annotations": {
                                "bold": false,
                                "italic": false,
                                "strikethrough": false,
                                "underline": false,
                                "code": false,
                                "color": "default"
                            },
                            "plain_text": "grind",
                            "href": null
                        }
                    ]
                }
            },
            "url": "https://www.notion.so/grind-63564486ecf84983826cdb383b49da92",
            "public_url": "https://foam-salamander-68d.notion.site/grind-63564486ecf84983826cdb383b49da92"
        },
        {
            "object": "page",
            "id": "6d9a0fd9-d4a4-40cb-ada8-17597c30bb18",
            "created_time": "2024-02-18T09:44:00.000Z",
            "last_edited_time": "2024-02-18T10:04:00.000Z",
            "created_by": {
                "object": "user",
                "id": "c83264a1-1c18-4e62-b06f-09afb04553ab"
            },
            "last_edited_by": {
                "object": "user",
                "id": "c83264a1-1c18-4e62-b06f-09afb04553ab"
            },
            "cover": null,
            "icon": null,
            "parent": {
                "type": "database_id",
                "database_id": "5d5f91b2-48ff-4656-9cc5-f0508bec0abc"
            },
            "archived": false,
            "properties": {
                "Start Time": {
                    "id": "V%40vk",
                    "type": "date",
                    "date": {
                        "start": "2024-02-05T22:30:00.000+00:00",
                        "end": null,
                        "time_zone": null
                    }
                },
                "End Time": {
                    "id": "WtZF",
                    "type": "date",
                    "date": {
                        "start": "2024-02-06T00:30:00.000+00:00",
                        "end": null,
                        "time_zone": null
                    }
                },
                "Title": {
                    "id": "title",
                    "type": "title",
                    "title": [
                        {
                            "type": "text",
                            "text": {
                                "content": "testing product",
                                "link": null
                            },
                            "annotations": {
                                "bold": false,
                                "italic": false,
                                "strikethrough": false,
                                "underline": false,
                                "code": false,
                                "color": "default"
                            },
                            "plain_text": "testing product",
                            "href": null
                        }
                    ]
                }
            },
            "url": "https://www.notion.so/testing-product-6d9a0fd9d4a440cbada817597c30bb18",
            "public_url": "https://foam-salamander-68d.notion.site/testing-product-6d9a0fd9d4a440cbada817597c30bb18"
        },
        {
            "object": "page",
            "id": "fff05454-253d-46a3-b1e4-bf946c178da6",
            "created_time": "2024-02-18T09:44:00.000Z",
            "last_edited_time": "2024-02-18T10:04:00.000Z",
            "created_by": {
                "object": "user",
                "id": "c83264a1-1c18-4e62-b06f-09afb04553ab"
            },
            "last_edited_by": {
                "object": "user",
                "id": "c83264a1-1c18-4e62-b06f-09afb04553ab"
            },
            "cover": null,
            "icon": null,
            "parent": {
                "type": "database_id",
                "database_id": "5d5f91b2-48ff-4656-9cc5-f0508bec0abc"
            },
            "archived": false,
            "properties": {
                "Start Time": {
                    "id": "V%40vk",
                    "type": "date",
                    "date": {
                        "start": "2024-02-09T18:45:00.000+00:00",
                        "end": null,
                        "time_zone": null
                    }
                },
                "End Time": {
                    "id": "WtZF",
                    "type": "date",
                    "date": {
                        "start": "2024-02-09T21:00:00.000+00:00",
                        "end": null,
                        "time_zone": null
                    }
                },
                "Title": {
                    "id": "title",
                    "type": "title",
                    "title": [
                        {
                            "type": "text",
                            "text": {
                                "content": "talking to mom",
                                "link": null
                            },
                            "annotations": {
                                "bold": false,
                                "italic": false,
                                "strikethrough": false,
                                "underline": false,
                                "code": false,
                                "color": "default"
                            },
                            "plain_text": "talking to mom",
                            "href": null
                        }
                    ]
                }
            },
            "url": "https://www.notion.so/talking-to-mom-fff05454253d46a3b1e4bf946c178da6",
            "public_url": "https://foam-salamander-68d.notion.site/talking-to-mom-fff05454253d46a3b1e4bf946c178da6"
        },
        {
            "object": "page",
            "id": "579fbad6-fa97-4127-a3c7-04641c491417",
            "created_time": "2024-02-18T09:43:00.000Z",
            "last_edited_time": "2024-02-18T10:04:00.000Z",
            "created_by": {
                "object": "user",
                "id": "c83264a1-1c18-4e62-b06f-09afb04553ab"
            },
            "last_edited_by": {
                "object": "user",
                "id": "c83264a1-1c18-4e62-b06f-09afb04553ab"
            },
            "cover": null,
            "icon": null,
            "parent": {
                "type": "database_id",
                "database_id": "5d5f91b2-48ff-4656-9cc5-f0508bec0abc"
            },
            "archived": false,
            "properties": {
                "Start Time": {
                    "id": "V%40vk",
                    "type": "date",
                    "date": {
                        "start": "2024-02-07T21:30:00.000+00:00",
                        "end": null,
                        "time_zone": null
                    }
                },
                "End Time": {
                    "id": "WtZF",
                    "type": "date",
                    "date": {
                        "start": "2024-02-08T02:15:00.000+00:00",
                        "end": null,
                        "time_zone": null
                    }
                },
                "Title": {
                    "id": "title",
                    "type": "title",
                    "title": [
                        {
                            "type": "text",
                            "text": {
                                "content": "grind",
                                "link": null
                            },
                            "annotations": {
                                "bold": false,
                                "italic": false,
                                "strikethrough": false,
                                "underline": false,
                                "code": false,
                                "color": "default"
                            },
                            "plain_text": "grind",
                            "href": null
                        }
                    ]
                }
            },
            "url": "https://www.notion.so/grind-579fbad6fa974127a3c704641c491417",
            "public_url": "https://foam-salamander-68d.notion.site/grind-579fbad6fa974127a3c704641c491417"
        },
        {
            "object": "page",
            "id": "b87a6265-721d-40da-bcc7-67ccb8484773",
            "created_time": "2024-02-18T09:43:00.000Z",
            "last_edited_time": "2024-02-18T10:04:00.000Z",
            "created_by": {
                "object": "user",
                "id": "c83264a1-1c18-4e62-b06f-09afb04553ab"
            },
            "last_edited_by": {
                "object": "user",
                "id": "c83264a1-1c18-4e62-b06f-09afb04553ab"
            },
            "cover": null,
            "icon": null,
            "parent": {
                "type": "database_id",
                "database_id": "5d5f91b2-48ff-4656-9cc5-f0508bec0abc"
            },
            "archived": false,
            "properties": {
                "Start Time": {
                    "id": "V%40vk",
                    "type": "date",
                    "date": {
                        "start": "2024-02-12T19:15:00.000+00:00",
                        "end": null,
                        "time_zone": null
                    }
                },
                "End Time": {
                    "id": "WtZF",
                    "type": "date",
                    "date": {
                        "start": "2024-02-12T20:00:00.000+00:00",
                        "end": null,
                        "time_zone": null
                    }
                },
                "Title": {
                    "id": "title",
                    "type": "title",
                    "title": [
                        {
                            "type": "text",
                            "text": {
                                "content": "emailing Obama",
                                "link": null
                            },
                            "annotations": {
                                "bold": false,
                                "italic": false,
                                "strikethrough": false,
                                "underline": false,
                                "code": false,
                                "color": "default"
                            },
                            "plain_text": "emailing Obama",
                            "href": null
                        }
                    ]
                }
            },
            "url": "https://www.notion.so/emailing-Obama-b87a6265721d40dabcc767ccb8484773",
            "public_url": "https://foam-salamander-68d.notion.site/emailing-Obama-b87a6265721d40dabcc767ccb8484773"
        },
        {
            "object": "page",
            "id": "45795438-f46a-4035-a8f1-458ed5d2011d",
            "created_time": "2024-02-18T09:43:00.000Z",
            "last_edited_time": "2024-02-18T10:04:00.000Z",
            "created_by": {
                "object": "user",
                "id": "c83264a1-1c18-4e62-b06f-09afb04553ab"
            },
            "last_edited_by": {
                "object": "user",
                "id": "c83264a1-1c18-4e62-b06f-09afb04553ab"
            },
            "cover": null,
            "icon": null,
            "parent": {
                "type": "database_id",
                "database_id": "5d5f91b2-48ff-4656-9cc5-f0508bec0abc"
            },
            "archived": false,
            "properties": {
                "Start Time": {
                    "id": "V%40vk",
                    "type": "date",
                    "date": {
                        "start": "2024-02-15T21:15:00.000+00:00",
                        "end": null,
                        "time_zone": null
                    }
                },
                "End Time": {
                    "id": "WtZF",
                    "type": "date",
                    "date": {
                        "start": "2024-02-15T23:00:00.000+00:00",
                        "end": null,
                        "time_zone": null
                    }
                },
                "Title": {
                    "id": "title",
                    "type": "title",
                    "title": [
                        {
                            "type": "text",
                            "text": {
                                "content": "user interview",
                                "link": null
                            },
                            "annotations": {
                                "bold": false,
                                "italic": false,
                                "strikethrough": false,
                                "underline": false,
                                "code": false,
                                "color": "default"
                            },
                            "plain_text": "user interview",
                            "href": null
                        }
                    ]
                }
            },
            "url": "https://www.notion.so/user-interview-45795438f46a4035a8f1458ed5d2011d",
            "public_url": "https://foam-salamander-68d.notion.site/user-interview-45795438f46a4035a8f1458ed5d2011d"
        },
        {
            "object": "page",
            "id": "861ecb7c-f113-4abf-b5ac-c8cabf4fb145",
            "created_time": "2024-02-18T09:43:00.000Z",
            "last_edited_time": "2024-02-18T10:04:00.000Z",
            "created_by": {
                "object": "user",
                "id": "c83264a1-1c18-4e62-b06f-09afb04553ab"
            },
            "last_edited_by": {
                "object": "user",
                "id": "c83264a1-1c18-4e62-b06f-09afb04553ab"
            },
            "cover": null,
            "icon": null,
            "parent": {
                "type": "database_id",
                "database_id": "5d5f91b2-48ff-4656-9cc5-f0508bec0abc"
            },
            "archived": false,
            "properties": {
                "Start Time": {
                    "id": "V%40vk",
                    "type": "date",
                    "date": {
                        "start": "2024-02-14T23:30:00.000+00:00",
                        "end": null,
                        "time_zone": null
                    }
                },
                "End Time": {
                    "id": "WtZF",
                    "type": "date",
                    "date": {
                        "start": "2024-02-15T00:30:00.000+00:00",
                        "end": null,
                        "time_zone": null
                    }
                },
                "Title": {
                    "id": "title",
                    "type": "title",
                    "title": [
                        {
                            "type": "text",
                            "text": {
                                "content": "marketing",
                                "link": null
                            },
                            "annotations": {
                                "bold": false,
                                "italic": false,
                                "strikethrough": false,
                                "underline": false,
                                "code": false,
                                "color": "default"
                            },
                            "plain_text": "marketing",
                            "href": null
                        }
                    ]
                }
            },
            "url": "https://www.notion.so/marketing-861ecb7cf1134abfb5acc8cabf4fb145",
            "public_url": "https://foam-salamander-68d.notion.site/marketing-861ecb7cf1134abfb5acc8cabf4fb145"
        },
        {
            "object": "page",
            "id": "c1c41ac9-3f79-4369-91bd-6b20d17f328f",
            "created_time": "2024-02-18T09:43:00.000Z",
            "last_edited_time": "2024-02-18T10:04:00.000Z",
            "created_by": {
                "object": "user",
                "id": "c83264a1-1c18-4e62-b06f-09afb04553ab"
            },
            "last_edited_by": {
                "object": "user",
                "id": "c83264a1-1c18-4e62-b06f-09afb04553ab"
            },
            "cover": null,
            "icon": null,
            "parent": {
                "type": "database_id",
                "database_id": "5d5f91b2-48ff-4656-9cc5-f0508bec0abc"
            },
            "archived": false,
            "properties": {
                "Start Time": {
                    "id": "V%40vk",
                    "type": "date",
                    "date": {
                        "start": "2024-02-13T00:00:00.000+00:00",
                        "end": null,
                        "time_zone": null
                    }
                },
                "End Time": {
                    "id": "WtZF",
                    "type": "date",
                    "date": {
                        "start": "2024-02-13T02:00:00.000+00:00",
                        "end": null,
                        "time_zone": null
                    }
                },
                "Title": {
                    "id": "title",
                    "type": "title",
                    "title": [
                        {
                            "type": "text",
                            "text": {
                                "content": "doing some study",
                                "link": null
                            },
                            "annotations": {
                                "bold": false,
                                "italic": false,
                                "strikethrough": false,
                                "underline": false,
                                "code": false,
                                "color": "default"
                            },
                            "plain_text": "doing some study",
                            "href": null
                        }
                    ]
                }
            },
            "url": "https://www.notion.so/doing-some-study-c1c41ac93f79436991bd6b20d17f328f",
            "public_url": "https://foam-salamander-68d.notion.site/doing-some-study-c1c41ac93f79436991bd6b20d17f328f"
        },
        {
            "object": "page",
            "id": "9e1ecd6c-dc3a-4a3e-9f39-4fe2a425d763",
            "created_time": "2024-02-18T09:43:00.000Z",
            "last_edited_time": "2024-02-18T10:04:00.000Z",
            "created_by": {
                "object": "user",
                "id": "c83264a1-1c18-4e62-b06f-09afb04553ab"
            },
            "last_edited_by": {
                "object": "user",
                "id": "c83264a1-1c18-4e62-b06f-09afb04553ab"
            },
            "cover": null,
            "icon": null,
            "parent": {
                "type": "database_id",
                "database_id": "5d5f91b2-48ff-4656-9cc5-f0508bec0abc"
            },
            "archived": false,
            "properties": {
                "Start Time": {
                    "id": "V%40vk",
                    "type": "date",
                    "date": {
                        "start": "2024-02-13T21:00:00.000+00:00",
                        "end": null,
                        "time_zone": null
                    }
                },
                "End Time": {
                    "id": "WtZF",
                    "type": "date",
                    "date": {
                        "start": "2024-02-13T23:00:00.000+00:00",
                        "end": null,
                        "time_zone": null
                    }
                },
                "Title": {
                    "id": "title",
                    "type": "title",
                    "title": [
                        {
                            "type": "text",
                            "text": {
                                "content": "some work",
                                "link": null
                            },
                            "annotations": {
                                "bold": false,
                                "italic": false,
                                "strikethrough": false,
                                "underline": false,
                                "code": false,
                                "color": "default"
                            },
                            "plain_text": "some work",
                            "href": null
                        }
                    ]
                }
            },
            "url": "https://www.notion.so/some-work-9e1ecd6cdc3a4a3e9f394fe2a425d763",
            "public_url": "https://foam-salamander-68d.notion.site/some-work-9e1ecd6cdc3a4a3e9f394fe2a425d763"
        },
        {
            "object": "page",
            "id": "6d86dd54-46a8-42e8-a13b-805626fc6c8a",
            "created_time": "2024-02-18T09:30:00.000Z",
            "last_edited_time": "2024-02-18T10:04:00.000Z",
            "created_by": {
                "object": "user",
                "id": "c83264a1-1c18-4e62-b06f-09afb04553ab"
            },
            "last_edited_by": {
                "object": "user",
                "id": "c83264a1-1c18-4e62-b06f-09afb04553ab"
            },
            "cover": null,
            "icon": null,
            "parent": {
                "type": "database_id",
                "database_id": "5d5f91b2-48ff-4656-9cc5-f0508bec0abc"
            },
            "archived": false,
            "properties": {
                "Start Time": {
                    "id": "V%40vk",
                    "type": "date",
                    "date": {
                        "start": "2024-02-18T09:08:00.000+00:00",
                        "end": null,
                        "time_zone": null
                    }
                },
                "End Time": {
                    "id": "WtZF",
                    "type": "date",
                    "date": {
                        "start": "2024-02-18T09:38:00.000+00:00",
                        "end": null,
                        "time_zone": null
                    }
                },
                "Title": {
                    "id": "title",
                    "type": "title",
                    "title": [
                        {
                            "type": "text",
                            "text": {
                                "content": "yoyoyo",
                                "link": null
                            },
                            "annotations": {
                                "bold": false,
                                "italic": false,
                                "strikethrough": false,
                                "underline": false,
                                "code": false,
                                "color": "default"
                            },
                            "plain_text": "yoyoyo",
                            "href": null
                        }
                    ]
                }
            },
            "url": "https://www.notion.so/yoyoyo-6d86dd5446a842e8a13b805626fc6c8a",
            "public_url": "https://foam-salamander-68d.notion.site/yoyoyo-6d86dd5446a842e8a13b805626fc6c8a"
        },
        {
            "object": "page",
            "id": "942d587a-fdb0-45cf-a1f2-09d8b57e193c",
            "created_time": "2024-02-18T09:26:00.000Z",
            "last_edited_time": "2024-02-18T10:04:00.000Z",
            "created_by": {
                "object": "user",
                "id": "c83264a1-1c18-4e62-b06f-09afb04553ab"
            },
            "last_edited_by": {
                "object": "user",
                "id": "c83264a1-1c18-4e62-b06f-09afb04553ab"
            },
            "cover": null,
            "icon": null,
            "parent": {
                "type": "database_id",
                "database_id": "5d5f91b2-48ff-4656-9cc5-f0508bec0abc"
            },
            "archived": false,
            "properties": {
                "Start Time": {
                    "id": "V%40vk",
                    "type": "date",
                    "date": {
                        "start": "2024-02-18T01:00:00.000+00:00",
                        "end": null,
                        "time_zone": null
                    }
                },
                "End Time": {
                    "id": "WtZF",
                    "type": "date",
                    "date": {
                        "start": "2024-02-18T02:00:00.000+00:00",
                        "end": null,
                        "time_zone": null
                    }
                },
                "Title": {
                    "id": "title",
                    "type": "title",
                    "title": [
                        {
                            "type": "text",
                            "text": {
                                "content": "howdy world!",
                                "link": null
                            },
                            "annotations": {
                                "bold": false,
                                "italic": false,
                                "strikethrough": false,
                                "underline": false,
                                "code": false,
                                "color": "default"
                            },
                            "plain_text": "howdy world!",
                            "href": null
                        }
                    ]
                }
            },
            "url": "https://www.notion.so/howdy-world-942d587afdb045cfa1f209d8b57e193c",
            "public_url": "https://foam-salamander-68d.notion.site/howdy-world-942d587afdb045cfa1f209d8b57e193c"
        },
        {
            "object": "page",
            "id": "ac5a7f4c-9f50-48a1-8289-62db3e74fba0",
            "created_time": "2024-02-18T08:53:00.000Z",
            "last_edited_time": "2024-02-18T10:04:00.000Z",
            "created_by": {
                "object": "user",
                "id": "c83264a1-1c18-4e62-b06f-09afb04553ab"
            },
            "last_edited_by": {
                "object": "user",
                "id": "c83264a1-1c18-4e62-b06f-09afb04553ab"
            },
            "cover": null,
            "icon": null,
            "parent": {
                "type": "database_id",
                "database_id": "5d5f91b2-48ff-4656-9cc5-f0508bec0abc"
            },
            "archived": false,
            "properties": {
                "Start Time": {
                    "id": "V%40vk",
                    "type": "date",
                    "date": {
                        "start": "2024-02-18T00:00:00.000+00:00",
                        "end": null,
                        "time_zone": null
                    }
                },
                "End Time": {
                    "id": "WtZF",
                    "type": "date",
                    "date": {
                        "start": "2024-02-18T01:00:00.000+00:00",
                        "end": null,
                        "time_zone": null
                    }
                },
                "Title": {
                    "id": "title",
                    "type": "title",
                    "title": [
                        {
                            "type": "text",
                            "text": {
                                "content": "test test test",
                                "link": null
                            },
                            "annotations": {
                                "bold": false,
                                "italic": false,
                                "strikethrough": false,
                                "underline": false,
                                "code": false,
                                "color": "default"
                            },
                            "plain_text": "test test test",
                            "href": null
                        }
                    ]
                }
            },
            "url": "https://www.notion.so/test-test-test-ac5a7f4c9f5048a1828962db3e74fba0",
            "public_url": "https://foam-salamander-68d.notion.site/test-test-test-ac5a7f4c9f5048a1828962db3e74fba0"
        },
        {
            "object": "page",
            "id": "f20cc26f-8a1f-4d0c-8e46-c7d2ed8c66a6",
            "created_time": "2024-02-18T02:39:00.000Z",
            "last_edited_time": "2024-02-18T10:04:00.000Z",
            "created_by": {
                "object": "user",
                "id": "c83264a1-1c18-4e62-b06f-09afb04553ab"
            },
            "last_edited_by": {
                "object": "user",
                "id": "c83264a1-1c18-4e62-b06f-09afb04553ab"
            },
            "cover": null,
            "icon": null,
            "parent": {
                "type": "database_id",
                "database_id": "5d5f91b2-48ff-4656-9cc5-f0508bec0abc"
            },
            "archived": false,
            "properties": {
                "Start Time": {
                    "id": "V%40vk",
                    "type": "date",
                    "date": {
                        "start": "2024-02-17T19:00:00.000+00:00",
                        "end": null,
                        "time_zone": null
                    }
                },
                "End Time": {
                    "id": "WtZF",
                    "type": "date",
                    "date": {
                        "start": "2024-02-17T19:30:00.000+00:00",
                        "end": null,
                        "time_zone": null
                    }
                },
                "Title": {
                    "id": "title",
                    "type": "title",
                    "title": [
                        {
                            "type": "text",
                            "text": {
                                "content": "donut time!",
                                "link": null
                            },
                            "annotations": {
                                "bold": false,
                                "italic": false,
                                "strikethrough": false,
                                "underline": false,
                                "code": false,
                                "color": "default"
                            },
                            "plain_text": "donut time!",
                            "href": null
                        }
                    ]
                }
            },
            "url": "https://www.notion.so/donut-time-f20cc26f8a1f4d0c8e46c7d2ed8c66a6",
            "public_url": "https://foam-salamander-68d.notion.site/donut-time-f20cc26f8a1f4d0c8e46c7d2ed8c66a6"
        },
        {
            "object": "page",
            "id": "e4e495fb-5077-44d2-923f-95eebbe4a62e",
            "created_time": "2024-02-18T02:38:00.000Z",
            "last_edited_time": "2024-02-18T10:04:00.000Z",
            "created_by": {
                "object": "user",
                "id": "c83264a1-1c18-4e62-b06f-09afb04553ab"
            },
            "last_edited_by": {
                "object": "user",
                "id": "c83264a1-1c18-4e62-b06f-09afb04553ab"
            },
            "cover": null,
            "icon": null,
            "parent": {
                "type": "database_id",
                "database_id": "5d5f91b2-48ff-4656-9cc5-f0508bec0abc"
            },
            "archived": false,
            "properties": {
                "Start Time": {
                    "id": "V%40vk",
                    "type": "date",
                    "date": {
                        "start": "2024-02-17T22:45:00.000+00:00",
                        "end": null,
                        "time_zone": null
                    }
                },
                "End Time": {
                    "id": "WtZF",
                    "type": "date",
                    "date": {
                        "start": "2024-02-18T00:00:00.000+00:00",
                        "end": null,
                        "time_zone": null
                    }
                },
                "Title": {
                    "id": "title",
                    "type": "title",
                    "title": [
                        {
                            "type": "text",
                            "text": {
                                "content": "pizza time!!!!",
                                "link": null
                            },
                            "annotations": {
                                "bold": false,
                                "italic": false,
                                "strikethrough": false,
                                "underline": false,
                                "code": false,
                                "color": "default"
                            },
                            "plain_text": "pizza time!!!!",
                            "href": null
                        }
                    ]
                }
            },
            "url": "https://www.notion.so/pizza-time-e4e495fb507744d2923f95eebbe4a62e",
            "public_url": "https://foam-salamander-68d.notion.site/pizza-time-e4e495fb507744d2923f95eebbe4a62e"
        },
        {
            "object": "page",
            "id": "2910f91c-fd03-42ce-aad0-c7e592ee66de",
            "created_time": "2024-02-18T02:35:00.000Z",
            "last_edited_time": "2024-02-18T10:04:00.000Z",
            "created_by": {
                "object": "user",
                "id": "c83264a1-1c18-4e62-b06f-09afb04553ab"
            },
            "last_edited_by": {
                "object": "user",
                "id": "c83264a1-1c18-4e62-b06f-09afb04553ab"
            },
            "cover": null,
            "icon": null,
            "parent": {
                "type": "database_id",
                "database_id": "5d5f91b2-48ff-4656-9cc5-f0508bec0abc"
            },
            "archived": false,
            "properties": {
                "Start Time": {
                    "id": "V%40vk",
                    "type": "date",
                    "date": {
                        "start": "2024-02-18T04:00:00.000+00:00",
                        "end": null,
                        "time_zone": null
                    }
                },
                "End Time": {
                    "id": "WtZF",
                    "type": "date",
                    "date": {
                        "start": "2024-02-18T06:00:00.000+00:00",
                        "end": null,
                        "time_zone": null
                    }
                },
                "Title": {
                    "id": "title",
                    "type": "title",
                    "title": [
                        {
                            "type": "text",
                            "text": {
                                "content": "ahahahahahah",
                                "link": null
                            },
                            "annotations": {
                                "bold": false,
                                "italic": false,
                                "strikethrough": false,
                                "underline": false,
                                "code": false,
                                "color": "default"
                            },
                            "plain_text": "ahahahahahah",
                            "href": null
                        }
                    ]
                }
            },
            "url": "https://www.notion.so/ahahahahahah-2910f91cfd0342ceaad0c7e592ee66de",
            "public_url": "https://foam-salamander-68d.notion.site/ahahahahahah-2910f91cfd0342ceaad0c7e592ee66de"
        },
        {
            "object": "page",
            "id": "a23d8613-93a5-4a99-a990-85ac1447ba1b",
            "created_time": "2024-02-18T02:19:00.000Z",
            "last_edited_time": "2024-02-18T10:04:00.000Z",
            "created_by": {
                "object": "user",
                "id": "c83264a1-1c18-4e62-b06f-09afb04553ab"
            },
            "last_edited_by": {
                "object": "user",
                "id": "c83264a1-1c18-4e62-b06f-09afb04553ab"
            },
            "cover": null,
            "icon": null,
            "parent": {
                "type": "database_id",
                "database_id": "5d5f91b2-48ff-4656-9cc5-f0508bec0abc"
            },
            "archived": false,
            "properties": {
                "Start Time": {
                    "id": "V%40vk",
                    "type": "date",
                    "date": {
                        "start": "2024-02-18T01:00:00.000+00:00",
                        "end": null,
                        "time_zone": null
                    }
                },
                "End Time": {
                    "id": "WtZF",
                    "type": "date",
                    "date": {
                        "start": "2024-02-18T02:45:00.000+00:00",
                        "end": null,
                        "time_zone": null
                    }
                },
                "Title": {
                    "id": "title",
                    "type": "title",
                    "title": [
                        {
                            "type": "text",
                            "text": {
                                "content": "Another test event",
                                "link": null
                            },
                            "annotations": {
                                "bold": false,
                                "italic": false,
                                "strikethrough": false,
                                "underline": false,
                                "code": false,
                                "color": "default"
                            },
                            "plain_text": "Another test event",
                            "href": null
                        }
                    ]
                }
            },
            "url": "https://www.notion.so/Another-test-event-a23d861393a54a99a99085ac1447ba1b",
            "public_url": "https://foam-salamander-68d.notion.site/Another-test-event-a23d861393a54a99a99085ac1447ba1b"
        },
        {
            "object": "page",
            "id": "f28dc24a-d2d4-4a44-8db8-f8e9328048ea",
            "created_time": "2024-02-18T02:18:00.000Z",
            "last_edited_time": "2024-02-18T10:04:00.000Z",
            "created_by": {
                "object": "user",
                "id": "c83264a1-1c18-4e62-b06f-09afb04553ab"
            },
            "last_edited_by": {
                "object": "user",
                "id": "c83264a1-1c18-4e62-b06f-09afb04553ab"
            },
            "cover": null,
            "icon": null,
            "parent": {
                "type": "database_id",
                "database_id": "5d5f91b2-48ff-4656-9cc5-f0508bec0abc"
            },
            "archived": false,
            "properties": {
                "Start Time": {
                    "id": "V%40vk",
                    "type": "date",
                    "date": {
                        "start": "2024-02-17T19:00:00.000+00:00",
                        "end": null,
                        "time_zone": null
                    }
                },
                "End Time": {
                    "id": "WtZF",
                    "type": "date",
                    "date": {
                        "start": "2024-02-17T21:00:00.000+00:00",
                        "end": null,
                        "time_zone": null
                    }
                },
                "Title": {
                    "id": "title",
                    "type": "title",
                    "title": [
                        {
                            "type": "text",
                            "text": {
                                "content": "test5",
                                "link": null
                            },
                            "annotations": {
                                "bold": false,
                                "italic": false,
                                "strikethrough": false,
                                "underline": false,
                                "code": false,
                                "color": "default"
                            },
                            "plain_text": "test5",
                            "href": null
                        }
                    ]
                }
            },
            "url": "https://www.notion.so/test5-f28dc24ad2d44a448db8f8e9328048ea",
            "public_url": "https://foam-salamander-68d.notion.site/test5-f28dc24ad2d44a448db8f8e9328048ea"
        }
    ],
    "next_cursor": null,
    "has_more": false,
    "type": "page_or_database",
    "page_or_database": {},
    "request_id": "65126319-50a3-4add-a39e-27b8abcd2359"
}