{
    "object": "page",
    "id": "93756543-928e-4f00-96bc-0e16b37dcc4e",
    "created_time": "2024-02-17T23:20:00.000Z",
    "last_edited_time": "2024-02-17T23:20:00.000Z",
    "created_by": {
        "object": "user",
        "id": "c83264a1-1c18-4e62-b06f-09afb04553ab"
    },
    "last_edited_by": {
        "object": "user",
        "id": "c83264a1-1c18-4e62-b06f-09afb04553ab"
    },
    "cover": null,
    "icon": null,
    "parent": {
        "type": "database_id",
        "database_id": "5d5f91b2-48ff-4656-9cc5-f0508bec0abc"
    },
    "archived": false,
    "properties": {
        "Start Time": {
            "id": "V%40vk",
            "type": "date",
            "date": {
                "start": "2024-02-17T10:00:00.000+00:00",
                "end": null,
                "time_zone": null
            }
        },
        "End Time": {
            "id": "WtZF",
            "type": "date",
            "date": {
                "start": "2024-02-17T12:00:00.000+00:00",
                "end": null,
                "time_zone": null
            }
        },
        "Title": {
            "id": "title",
            "type": "title",
            "title": [
                {
                    "type": "text",
                    "text": {
                        "content": "Test entry",
                        "link": null
                    },
                    "annotations": {
                        "bold": false,
                        "italic": false,
                        "strikethrough": false,
                        "underline": false,
                        "code": false,
                        "color": "default"
                    },
                    "plain_text": "Test entry",
                    "href": null
                }
            ]
        }
    },
    "url": "https://www.notion.so/Test-entry-93756543928e4f0096bc0e16b37dcc4e",
    "public_url": "https://foam-salamander-68d.notion.site/Test-entry-93756543928e4f0096bc0e16b37dcc4e",
    "request_id": "fca50a23-efdb-4302-8a6b-2abf7ca5801a"
}